[
    {
        "name": "Floor 1",
        "enemies": ["Forest Slime"],
        "gold": 40

    },
    {
        "name": "Floor 2",
        "enemies": ["Forest Slime", "Aqua Slime"],
        "gold": 50
       
    },
    {
        "name": "Floor 3",
        "enemies": ["Ember Slime"],
        "gold": 60
       
    },
    {
        "name": "Floor 4",
        "enemies": ["Forest Slime", "Forest Slime"],
        "gold": 70

    },
    {
        "name": "Floor 5",
        "enemies": ["Forest Slime","Ember Slime","Aqua Slime"],
        "gold": 80
    },
    {
        "name": "Floor 6",
        "enemies": ["Forest Slime"],
        "gold": 100

    }
   
]